py_positron/__init__.py
py_positron/__main__.py
py_positron/activate.py
py_positron/buildcmd.py
py_positron/cli.py
py_positron/create.py
py_positron/createvenv.py
py_positron/install.py
py_positron/python_executor.ps1
py_positron/startproj.py
py_positron/updatecmd.py
py_positron/winpackage_installer.ps1
py_positron/winvenv_setup.ps1
py_positron/example/checkmark.png
py_positron/example/index.html
py_positron/example/main_app.py
py_positron-0.0.2.3.dist-info/licenses/LICENSE
py_positron-0.0.2.3.dist-info/METADATA
py_positron-0.0.2.3.dist-info/WHEEL
py_positron-0.0.2.3.dist-info/entry_points.txt
py_positron-0.0.2.3.dist-info/top_level.txt
py_positron-0.0.2.3.dist-info/RECORD
